amzn_sagemaker_aiops_jupyterlab_extension/__init__.py
amzn_sagemaker_aiops_jupyterlab_extension/_version.py
amzn_sagemaker_aiops_jupyterlab_extension/clients.py
amzn_sagemaker_aiops_jupyterlab_extension/constants.py
amzn_sagemaker_aiops_jupyterlab_extension/exceptions.py
amzn_sagemaker_aiops_jupyterlab_extension/handlers.py
amzn_sagemaker_aiops_jupyterlab_extension/labextension/package.json
amzn_sagemaker_aiops_jupyterlab_extension/labextension/static/242.b1b4354fe998962834d3.js
amzn_sagemaker_aiops_jupyterlab_extension/labextension/static/696.bbd9009e8edae8b78a80.js
amzn_sagemaker_aiops_jupyterlab_extension/labextension/static/remoteEntry.fed62c7d9ebcc7c32670.js
amzn_sagemaker_aiops_jupyterlab_extension/labextension/static/style.js
amzn_sagemaker_aiops_jupyterlab_extension/labextension/static/third-party-licenses.json
amzn_sagemaker_aiops_jupyterlab_extension/utils/__init__.py
amzn_sagemaker_aiops_jupyterlab_extension/utils/app_metadata.py
amzn_sagemaker_aiops_jupyterlab_extension/utils/file_watcher.py
amzn_sagemaker_aiops_jupyterlab_extension/utils/pipelines_output_util.py
amzn_sagemaker_aiops_jupyterlab_extension-1.0.4.data/data/etc/jupyter/jupyter_server_config.d/amzn_sagemaker_aiops_jupyterlab_extension.json
amzn_sagemaker_aiops_jupyterlab_extension-1.0.4.data/data/share/jupyter/labextensions/@amzn/amzn_sagemaker_aiops_jupyterlab_extension/package.json
amzn_sagemaker_aiops_jupyterlab_extension-1.0.4.data/data/share/jupyter/labextensions/@amzn/amzn_sagemaker_aiops_jupyterlab_extension/static/242.b1b4354fe998962834d3.js
amzn_sagemaker_aiops_jupyterlab_extension-1.0.4.data/data/share/jupyter/labextensions/@amzn/amzn_sagemaker_aiops_jupyterlab_extension/static/696.bbd9009e8edae8b78a80.js
amzn_sagemaker_aiops_jupyterlab_extension-1.0.4.data/data/share/jupyter/labextensions/@amzn/amzn_sagemaker_aiops_jupyterlab_extension/static/remoteEntry.fed62c7d9ebcc7c32670.js
amzn_sagemaker_aiops_jupyterlab_extension-1.0.4.dist-info/METADATA
amzn_sagemaker_aiops_jupyterlab_extension-1.0.4.dist-info/WHEEL
amzn_sagemaker_aiops_jupyterlab_extension-1.0.4.dist-info/licenses/LICENSE
amzn_sagemaker_aiops_jupyterlab_extension-1.0.4.dist-info/RECORD
